morse/Morse.py
morse/__init__.py
morsecode_package-1.0.0.dist-info/LICENSE
morsecode_package-1.0.0.dist-info/METADATA
morsecode_package-1.0.0.dist-info/WHEEL
morsecode_package-1.0.0.dist-info/top_level.txt
morsecode_package-1.0.0.dist-info/RECORD
