Metadata-Version: 2.1
Name: morsecode-package
Version: 1.0.0
Summary: Python package for converting text to Morse code and vice versa
Home-page: https://github.com/rahulaauji-30/morse.git
Author: Rahul Parihar
Author-email: rahulaauji71@gmail.com
License: MIT
Keywords: morse-code text-processing
Classifier: Development Status :: 3 - Alpha
Classifier: License :: OSI Approved :: MIT License
Classifier: Programming Language :: Python :: 3
Classifier: Programming Language :: Python :: 3.6
Classifier: Programming Language :: Python :: 3.7
Classifier: Programming Language :: Python :: 3.8
Classifier: Programming Language :: Python :: 3.9
Classifier: Programming Language :: Python :: 3.10
Classifier: Topic :: Text Processing
Requires-Python: >=3.6
License-File: LICENSE
